pystuff/__init__.py
pystuff-0.0.7.dist-info/LICENSE
pystuff-0.0.7.dist-info/METADATA
pystuff-0.0.7.dist-info/WHEEL
pystuff-0.0.7.dist-info/top_level.txt
pystuff-0.0.7.dist-info/RECORD
