Metadata-Version: 2.1
Name: pystuff
Version: 0.0.7
Summary: Some useful functions for data analysis in python.
Home-page: https://github.com/davidmnielsen/pystuff
Author: David Nielsen
Author-email: davidnielsen@id.uff.br
License: UNKNOWN
Platform: UNKNOWN
Classifier: Programming Language :: Python :: 3
Classifier: License :: OSI Approved :: MIT License
Classifier: Operating System :: OS Independent
Requires-Dist: numpy
Requires-Dist: matplotlib
Requires-Dist: xarray
Requires-Dist: pandas
Requires-Dist: scipy
